CHANGELOG.txt
LICENCE.txt
MANIFEST.in
README.txt
Readme.md
setup.py
DrowsinessDetection/DrowsinessDetector.py
DrowsinessDetection/__init__.py
DrowsinessDetection/Models/ParallelProcessing.py
DrowsinessDetection/Models/__init__.py
DrowsinessDetection/Models/cnnCat4.h5
DrowsinessDetection/SoundSystem/AudioCommands.py
DrowsinessDetection/SoundSystem/SoundManager.py
DrowsinessDetection/SoundSystem/__init__.py
DrowsinessDetection/SoundSystem/alarm.wav
DrowsinessDetection/haar cascade files/haarcascade_frontalface_alt.xml
DrowsinessDetection/haar cascade files/haarcascade_lefteye_2splits.xml
DrowsinessDetection/haar cascade files/haarcascade_righteye_2splits.xml
python_DrowsyDetection.egg-info/PKG-INFO
python_DrowsyDetection.egg-info/SOURCES.txt
python_DrowsyDetection.egg-info/dependency_links.txt
python_DrowsyDetection.egg-info/requires.txt
python_DrowsyDetection.egg-info/top_level.txt