Metadata-Version: 2.1
Name: python-DrowsyDetection
Version: 0.1.4
Summary: Library for drowsiness detection using deep learning
Home-page: UNKNOWN
Author: Ajit Singh Rathore
Author-email: ajitsinghrathore64277@gmail.com
License: MIT
Keywords: Drowsiness
Platform: UNKNOWN
Classifier: Development Status :: 5 - Production/Stable
Classifier: Intended Audience :: Education
Classifier: Operating System :: Microsoft :: Windows :: Windows 10
Classifier: License :: OSI Approved :: MIT License
Classifier: Programming Language :: Python :: 3
